lab1/my_add.v
module my_add #(
	parameter BITWIDTH = 32
)
(
	input [BITWIDTH-1:0] ain,
	input [BITWIDTH-1:0] bin,
	output [BITWIDTH-1:0] dout,
	output overflow
);

assign {overflow, dout} = ain + bin;

endmodule

lab1/my_add_tb.v
// Verilog test bench for example_3_1
`timescale 1ns/100ps
`include "my_add.v"

module my_add_tb;
  parameter BITWIDTH = 32;
  parameter TESTCOUNT = 8;

  reg [BITWIDTH-1:0] ain, bin;
  wire [BITWIDTH-1:0] dout;
  wire overflow;

  my_add UUT(ain, bin, dout, overflow);

  integer i;

  initial begin
    ain = 'hffffffff;
    bin = 'h1;

    $dumpfile("my_add_tb.vcd");
    $dumpvars(0, my_add_tb);
    for (i=0; i<TESTCOUNT; i=i+1) begin
      ain = $random%'hffffffff;
      bin = $random%'hffffffff;
      #10;
      $display("ain: %h / bin: %h / dout: %h / overflow: %h", ain, bin, dout, overflow);
    end

    $finish;
  end

endmodule

lab1/my_add_tb.vcd
$date
	Wed Mar 15 20:56:43 2017
$end
$version
	Icarus Verilog
$end
$timescale
	100ps
$end
$scope module my_add_tb $end
$var wire 1 ! overflow $end
$var wire 32 " dout [31:0] $end
$var reg 32 # ain [31:0] $end
$var reg 32 $ bin [31:0] $end
$var integer 32 % i [31:0] $end
$scope module UUT $end
$var wire 32 & ain [31:0] $end
$var wire 32 ' bin [31:0] $end
$var wire 1 ! overflow $end
$var wire 32 ( dout [31:0] $end
$upscope $end
$upscope $end
$enddefinitions $end
#0
$dumpvars
b11010010100111101001001110100101 (
b11000000100010010101111010000001 '
b10010000101010011010100100100 &
b0 %
b11000000100010010101111010000001 $
b10010000101010011010100100100 #
b11010010100111101001001110100101 "
0!
$end
#100
b110110011101010010110001101100 "
b110110011101010010110001101100 (
1!
b10110001111100000101011001100011 $
b10110001111100000101011001100011 '
b10000100100001001101011000001001 #
b10000100100001001101011000001001 &
b1 %
#200
b1001101100110010001010010011010 "
b1001101100110010001010010011010 (
0!
b1000110110111111001100110001101 $
b1000110110111111001100110001101 '
b110101110010111101100001101 #
b110101110010111101100001101 &
b10 %
#300
1!
b111011111110011101011001110111 "
b111011111110011101011001110111 (
b10001001001101110101001000010010 $
b10001001001101110101001000010010 '
b10110010110000101000010001100101 #
b10110010110000101000010001100101 &
b11 %
#400
b111110010111011000000001110 "
b111110010111011000000001110 (
0!
b110110101111100110100001101 $
b110110101111100110100001101 '
b111100111110001100000001 #
b111100111110001100000001 &
b100 %
#500
b1011001101100011011111010110011 "
b1011001101100011011111010110011 (
b11110100011011100110100111101 $
b11110100011011100110100111101 '
b111011001000111111000101110110 #
b111011001000111111000101110110 &
b101 %
#600
b10111101000000100100111101111001 "
b10111101000000100100111101111001 (
b1000110001011011111011110001100 $
b1000110001011011111011110001100 '
b1110110110101000101011111101101 #
b1110110110101000101011111101101 &
b110 %
#700
1!
b1100000001101010000111010111111 "
b1100000001101010000111010111111 (
b11100011001101110010010011000110 $
b11100011001101110010010011000110 '
b1111100111111011110100111111001 #
b1111100111111011110100111111001 &
b111 %
#800
b1000 %
