lab1/my_mul.v
module my_mul #(
	parameter BITWIDTH = 32
)
(
	input [BITWIDTH-1:0] ain,
	input [BITWIDTH-1:0] bin,
	output [BITWIDTH-1:0] dout,
	output overflow
);

wire [BITWIDTH*2-1:0] result = ain * bin;

assign {overflow, dout} = {|result[BITWIDTH*2-1:BITWIDTH], result[BITWIDTH-1:0]};

endmodule

lab1/my_mul_tb.v
// Verilog test bench for example_3_1
`timescale 1ns/100ps
`include "my_mul.v"

module my_mul_tb;
  parameter BITWIDTH = 32;
  parameter TESTCOUNT = 8;

  reg [BITWIDTH-1:0] ain, bin;
  wire [BITWIDTH-1:0] dout;
  wire overflow;

  my_mul UUT(ain, bin, dout, overflow);

  integer i;

  initial begin
    ain = 'hffffffff;
    bin = 'h1;

    $dumpfile("my_mul_tb.vcd");
    $dumpvars(0, my_mul_tb);
    for (i=0; i<TESTCOUNT; i=i+1) begin
      ain = $random%'hffff;
      bin = $random%'hfffff;
      #10;
      $display("ain: %h / bin: %h / dout: %h / overflow: %h", ain, bin, dout, overflow);
    end

    $finish;
  end

endmodule

lab1/my_mul_tb.vcd
$date
	Wed Mar 15 21:04:36 2017
$end
$version
	Icarus Verilog
$end
$timescale
	100ps
$end
$scope module my_mul_tb $end
$var wire 1 ! overflow $end
$var wire 32 " dout [31:0] $end
$var reg 32 # ain [31:0] $end
$var reg 32 $ bin [31:0] $end
$var integer 32 % i [31:0] $end
$scope module UUT $end
$var wire 32 & ain [31:0] $end
$var wire 32 ' bin [31:0] $end
$var wire 64 ( result [63:0] $end
$var wire 1 ! overflow $end
$var wire 32 ) dout [31:0] $end
$upscope $end
$upscope $end
$enddefinitions $end
#0
$dumpvars
b10011110101001001011011110000001 )
b1010011110101001001011011110000001 (
b10010110101010001001 '
b100011100111001 &
b0 %
b10010110101010001001 $
b100011100111001 #
b10011110101001001011011110000001 "
1!
$end
#100
0!
b100010011111011100101000011100 "
b100010011111011100101000011100 )
b110000110000010 $
b110000110000010 '
b100010011111011100101000011100 (
b101101010001110 #
b101101010001110 &
b1 %
#200
1!
b11101010101011110010100101011100 "
b11101010101011110010100101011100 )
b11111001110111111010 $
b11111001110111111010 '
b11111101010101011110010100101011100 (
b1000000111000110 #
b1000000111000110 &
b10 %
#300
b10010101100111111001110011001000 "
b10010101100111111001110011001000 )
b1110101101010100101 $
b1110101101010100101 '
b110010101100111111001110011001000 (
b11011100101000 #
b11011100101000 &
b11 %
#400
b11110010101000110000011001001000 "
b11110010101000110000011001001000 )
b1111100110101111010 $
b1111100110101111010 '
b11011110010101000110000011001001000 (
b1110001111110100 #
b1110001111110100 &
b100 %
#500
b1100111111010001111100001000010 "
b1100111111010001111100001000010 )
b11011100111100100101 $
b11011100111100100101 '
b1001100111111010001111100001000010 (
b10110010011010 #
b10110010011010 &
b101 %
#600
b1001011010001000111001001101110 "
b1001011010001000111001001101110 )
b11011111101111101110 $
b11011111101111101110 '
b101101001011010001000111001001101110 (
b1100111011000001 #
b1100111011000001 &
b110 %
#700
b11100101010000010110010000111111 "
b11100101010000010110010000111111 )
b1110011001011111001 $
b1110011001011111001 '
b1011100101010000010110010000111111 (
b110011011110111 #
b110011011110111 &
b111 %
#800
b1000 %
